vidhdr.py
vidhdr-1.0.1.dist-info/DESCRIPTION.rst
vidhdr-1.0.1.dist-info/RECORD
vidhdr-1.0.1.dist-info/metadata.json
vidhdr-1.0.1.dist-info/METADATA
vidhdr-1.0.1.dist-info/WHEEL
vidhdr-1.0.1.dist-info/top_level.txt
