Metadata-Version: 2.0
Name: vidhdr
Version: 1.0.1
Summary: Determine the type of a video
Home-page: https://github.com/Zack--/vidhdr
Author: Zack Dibe
Author-email: contact@zackdibe.com
License: MIT
Keywords: video header type mimetype imghdr
Platform: UNKNOWN
Classifier: Development Status :: 3 - Alpha
Classifier: Intended Audience :: Developers
Classifier: Topic :: Software Development :: Quality Assurance
Classifier: License :: OSI Approved :: MIT License
Classifier: Programming Language :: Python :: 2
Classifier: Programming Language :: Python :: 2.6
Classifier: Programming Language :: Python :: 2.7
Classifier: Programming Language :: Python :: 3
Classifier: Programming Language :: Python :: 3.3
Classifier: Programming Language :: Python :: 3.4
Classifier: Programming Language :: Python :: 3.5
